README.md
setup.py
rpi_d3m_primitives_part2/Bayesian_Classification.py
rpi_d3m_primitives_part2/CBN_Regression.py
rpi_d3m_primitives_part2/GCD_Classification.py
rpi_d3m_primitives_part2/GlobalCausalDiscovery.py
rpi_d3m_primitives_part2/__init__.py
rpi_d3m_primitives_part2.egg-info/PKG-INFO
rpi_d3m_primitives_part2.egg-info/SOURCES.txt
rpi_d3m_primitives_part2.egg-info/dependency_links.txt
rpi_d3m_primitives_part2.egg-info/entry_points.txt
rpi_d3m_primitives_part2.egg-info/requires.txt
rpi_d3m_primitives_part2.egg-info/top_level.txt
rpi_d3m_primitives_part2/Sampling/CandidateDAGs.py
rpi_d3m_primitives_part2/Sampling/LocalPosterior.py
rpi_d3m_primitives_part2/Sampling/MetropolisHastingSampler.py
rpi_d3m_primitives_part2/Sampling/MonteCarloSampler.py
rpi_d3m_primitives_part2/Sampling/Posterior.py
rpi_d3m_primitives_part2/Sampling/__init__.py
rpi_d3m_primitives_part2/Sampling/util.py
rpi_d3m_primitives_part2/causalDiscovery/__init__.py
rpi_d3m_primitives_part2/causalDiscovery/causaldiscovery_BayesEst.py
rpi_d3m_primitives_part2/featSelect/RelationSet.py
rpi_d3m_primitives_part2/featSelect/__init__.py
rpi_d3m_primitives_part2/featSelect/discretization.py
rpi_d3m_primitives_part2/featSelect/helperFunctions.py
rpi_d3m_primitives_part2/pyBN/__init__.py
rpi_d3m_primitives_part2/pyBN/classes/__init__.py
rpi_d3m_primitives_part2/pyBN/classes/bayesnet.py
rpi_d3m_primitives_part2/pyBN/classes/cliquetree.py
rpi_d3m_primitives_part2/pyBN/classes/clustergraph.py
rpi_d3m_primitives_part2/pyBN/classes/empiricaldistribution.py
rpi_d3m_primitives_part2/pyBN/classes/factor.py
rpi_d3m_primitives_part2/pyBN/classes/factorization.py
rpi_d3m_primitives_part2/pyBN/learning/__init__.py
rpi_d3m_primitives_part2/pyBN/learning/parameter/__init__.py
rpi_d3m_primitives_part2/pyBN/learning/parameter/bayes.py
rpi_d3m_primitives_part2/pyBN/learning/parameter/mle.py
rpi_d3m_primitives_part2/pyBN/learning/structure/__init__.py
rpi_d3m_primitives_part2/pyBN/learning/structure/mdbn.py
rpi_d3m_primitives_part2/pyBN/learning/structure/naive/TAN.py
rpi_d3m_primitives_part2/pyBN/learning/structure/naive/__init__.py
rpi_d3m_primitives_part2/pyBN/learning/structure/naive/naive_bayes.py
rpi_d3m_primitives_part2/pyBN/learning/structure/score/__init__.py
