Metadata-Version: 1.1
Name: rpi-d3m-primitives-part2
Version: 0.0.5
Summary: Partial RPI primitives for D3M. Including structured classifier and global causal discovery.
Home-page: https://gitlab.com/N.Yin/rpi-d3m-part2.git
Author: Naiyu Yin, Zijun Cui, Yuru Wang, Qiang Ji
Author-email: yinn2@rpi.edu
License: UNKNOWN
Keywords: d3m_primitive
Platform: Linux
Platform: MacOS
Classifier: License :: OSI Approved :: MIT License
Classifier: Operating System :: OS Independent
Classifier: Programming Language :: Python
